ipmi/__init__.py
ipmi/const.py
ipmi/format_func.py
ipmi/ipmi.py
ipmi/utils.py
ipmi-0.7.dist-info/DESCRIPTION.rst
ipmi-0.7.dist-info/METADATA
ipmi-0.7.dist-info/RECORD
ipmi-0.7.dist-info/WHEEL
ipmi-0.7.dist-info/entry_points.txt
ipmi-0.7.dist-info/metadata.json
ipmi-0.7.dist-info/top_level.txt
