Metadata-Version: 2.0
Name: ipmi
Version: 0.7
Summary: A ipmi python client used in NetXMS migrated from perl
Home-page: https://github.com/zhao-ji/check_ipmi_sensor_v3
Author: Trevor Max
Author-email: me@minganci.org
License: MIT
Keywords: ipmi netxms
Platform: UNKNOWN
